LICENSE
konfik/__init__.py
konfik-2.0.5.dist-info/entry_points.txt
konfik-2.0.5.dist-info/LICENSE
konfik-2.0.5.dist-info/WHEEL
konfik-2.0.5.dist-info/METADATA
konfik-2.0.5.dist-info/RECORD
