Metadata-Version: 2.1
Name: konfik
Version: 2.0.5
Summary: The Strangely Familiar Config Parser
Home-page: https://github.com/rednafi/konfik
License: MIT
Keywords: config,configuration,toml,dotenv,yaml
Author: rednafi
Author-email: redowan.nafi@gmail.com
Requires-Python: >=3.6,<4.0
Classifier: Environment :: Console
Classifier: License :: OSI Approved :: MIT License
Classifier: Operating System :: OS Independent
Classifier: Programming Language :: Python :: 3
Classifier: Programming Language :: Python :: 3.6
Classifier: Programming Language :: Python :: 3.7
Classifier: Programming Language :: Python :: 3.8
Classifier: Programming Language :: Python :: 3.9
Classifier: Topic :: Software Development
Classifier: Topic :: Software Development :: Libraries :: Python Modules
Classifier: Topic :: Software Development :: Quality Assurance
Requires-Dist: PyYAML (>=5.3.1,<6.0.0)
Requires-Dist: Pygments (>=2.7.3,<3.0.0)
Requires-Dist: python-dotenv (>=0.15.0,<0.16.0)
Requires-Dist: toml (>=0.10.2,<0.11.0)
Project-URL: Repository, https://github.com/rednafi/konfik
